roblox/__init__.py
roblox/account.py
roblox/assets.py
roblox/badges.py
roblox/chat.py
roblox/client.py
roblox/conversations.py
roblox/creatortype.py
roblox/delivery.py
roblox/friends.py
roblox/gamepasses.py
roblox/groups.py
roblox/instances.py
roblox/jobs.py
roblox/members.py
roblox/places.py
roblox/plugins.py
roblox/presence.py
roblox/promotionchannels.py
roblox/resale.py
roblox/robloxbadges.py
roblox/roles.py
roblox/shout.py
roblox/sociallinks.py
roblox/threedthumbnails.py
roblox/thumbnails.py
roblox/universes.py
roblox/users.py
roblox/wall.py
roblox/bases/__init__.py
roblox/bases/baseasset.py
roblox/bases/basebadge.py
roblox/bases/baseconversation.py
roblox/bases/basegamepass.py
roblox/bases/basegroup.py
roblox/bases/baseinstance.py
roblox/bases/baseitem.py
roblox/bases/basejob.py
roblox/bases/baseplace.py
roblox/bases/baseplugin.py
roblox/bases/baserobloxbadge.py
roblox/bases/baserole.py
roblox/bases/basesociallink.py
roblox/bases/baseuniverse.py
roblox/bases/baseuser.py
roblox/partials/__init__.py
roblox/partials/partialbadge.py
roblox/partials/partialgroup.py
roblox/partials/partialrole.py
roblox/partials/partialuniverse.py
roblox/partials/partialuser.py
roblox/utilities/__init__.py
roblox/utilities/exceptions.py
roblox/utilities/iterators.py
roblox/utilities/requests.py
roblox/utilities/shared.py
roblox/utilities/types.py
roblox/utilities/url.py
roblox-2.0.0.dist-info/LICENSE
roblox-2.0.0.dist-info/METADATA
roblox-2.0.0.dist-info/WHEEL
roblox-2.0.0.dist-info/top_level.txt
roblox-2.0.0.dist-info/RECORD
