Metadata-Version: 2.1
Name: roblox
Version: 2.0.0
Summary: ro.py is a modern object-oriented asynchronous Python wrapper for the Roblox web API.
Home-page: https://github.com/ro-py/ro.py
Author: jmkdev
Author-email: jmk@jmksite.dev
License: UNKNOWN
Project-URL: Discord, https://discord.gg/tjRfCbDMSk
Project-URL: Issue Tracker, https://github.com/ro-py/ro.py/issues
Project-URL: GitHub, https://github.com/ro-py/ro.py/
Project-URL: Examples, https://github.com/ro-py/ro.py/tree/main/examples
Project-URL: Twitter, https://twitter.com/jmkdev
Platform: UNKNOWN
Classifier: Programming Language :: Python :: 3
Classifier: License :: OSI Approved :: MIT License
Classifier: Operating System :: OS Independent
Classifier: Framework :: AsyncIO
Classifier: Topic :: Internet :: WWW/HTTP :: Dynamic Content :: CGI Tools/Libraries
Classifier: Topic :: Software Development :: Libraries
Requires-Python: >=3.7
License-File: LICENSE
